tableau/__init__.py
tableau/client.py
tableau_client_talenttech_oss-0.0.7.dist-info/LICENSE.txt
tableau_client_talenttech_oss-0.0.7.dist-info/METADATA
tableau_client_talenttech_oss-0.0.7.dist-info/WHEEL
tableau_client_talenttech_oss-0.0.7.dist-info/top_level.txt
tableau_client_talenttech_oss-0.0.7.dist-info/RECORD
