Metadata-Version: 2.1
Name: tableau-client-talenttech-oss
Version: 0.0.7
Summary: tableau dashboard extract updater
Home-page: https://github.com/severgroup-tt/topmind-commons
Author: Artem Gruzdov
Author-email: a.gruzdov@talenttech.ru
License: MIT
Platform: UNKNOWN
Classifier: Programming Language :: Python :: 3
Classifier: License :: OSI Approved :: MIT License
Classifier: Operating System :: OS Independent
Requires-Python: >=3.6
License-File: LICENSE.txt
Requires-Dist: tableauserverclient (==0.15.0)
